ts3API/Events.py
ts3API/SSHConnWrapper.py
ts3API/TS3Connection.py
ts3API/TS3QueryExceptionType.py
ts3API/__init__.py
ts3API/setup.py
ts3API/socket_wrapper.py
ts3API/utilities.py
ts3API-0.9.4.dist-info/LICENSE
ts3API-0.9.4.dist-info/METADATA
ts3API-0.9.4.dist-info/WHEEL
ts3API-0.9.4.dist-info/top_level.txt
ts3API-0.9.4.dist-info/RECORD
