Metadata-Version: 2.1
Name: ts3API
Version: 0.9.4
Summary: Python 3 API that allows interactive access to the TeamSpeak 3 Server Query interface.
Home-page: https://github.com/Murgeye/teamspeak3-python-api
Author: Fabian Ising, Daniel Lukats
Author-email: ts3API@murgi.de, ts3API@aethiles.de
License: Apache License 2.0
Keywords: TeamSpeak,ts3,ts3API,TeamSpeak3
Classifier: Programming Language :: Python :: 3
Classifier: License :: OSI Approved :: Apache Software License
Classifier: Operating System :: OS Independent
License-File: LICENSE
Requires-Dist: blinker (==1.4)
Provides-Extra: ssh
Requires-Dist: paramiko ; extra == 'ssh'
